mangadexSdk/__init__.py
mangadexSdk/constants.py
mangadexSdk/mangaDex.py
mangadexSdk/requestTypes.py
mangadexSdk/responseTypes.py
mangadexSdk/serializable.py
mangadexSdk-0.0.15.dist-info/LICENSE
mangadexSdk-0.0.15.dist-info/METADATA
mangadexSdk-0.0.15.dist-info/WHEEL
mangadexSdk-0.0.15.dist-info/top_level.txt
mangadexSdk-0.0.15.dist-info/RECORD
