Metadata-Version: 2.1
Name: mangadexSdk
Version: 0.0.15
Summary: An SDK for easily accessing information from the Mangadex v5 API.
Home-page: https://github.com/jasonfrancis/mangadexSDK
Author: Jason Francis
Author-email: jkfranci@gmail.com
Project-URL: Bug Tracker, https://github.com/jasonfrancis/mangadexSDK/issues
Classifier: Programming Language :: Python :: 3
Classifier: License :: OSI Approved :: MIT License
Classifier: Operating System :: OS Independent
Requires-Python: >=3.8
License-File: LICENSE
